lth_tools/__init__.py
lth_tools/cv_tools/Affine.py
lth_tools/cv_tools/__init__.py
lth_tools/pillow_tools/GaussianBlur.py
lth_tools/pillow_tools/GridMask.py
lth_tools/pillow_tools/MaskBlender.py
lth_tools/pillow_tools/YOCO.py
lth_tools/pillow_tools/__init__.py
lth_tools/torch_tools/CTC.py
lth_tools/torch_tools/GroupNorm.py
lth_tools/torch_tools/__init__.py
LTHTools-1.0.0.dist-info/METADATA
LTHTools-1.0.0.dist-info/WHEEL
LTHTools-1.0.0.dist-info/top_level.txt
LTHTools-1.0.0.dist-info/RECORD
